symbian_sports_tracker/__init__.py
symbian_sports_tracker/convert_nst_files_to_gpx.py
symbian_sports_tracker/convert_nst_rec_to_gpx.py
symbian_sports_tracker/mini_gpx.py
symbian_sports_tracker/nst.py
symbian_sports_tracker/scsu.py
symbian_sports_tracker-0.9.9.dist-info/LICENSE
symbian_sports_tracker-0.9.9.dist-info/METADATA
symbian_sports_tracker-0.9.9.dist-info/WHEEL
symbian_sports_tracker-0.9.9.dist-info/entry_points.txt
symbian_sports_tracker-0.9.9.dist-info/top_level.txt
symbian_sports_tracker-0.9.9.dist-info/RECORD
