Metadata-Version: 2.1
Name: symbian-sports-tracker
Version: 0.9.9
Summary: Read-Symbian-SportsTracker-file
Home-page: https://github.com/ekspla/Read-Symbian-SportsTracker-file
Author: ekspla
License: LGPL
Keywords: sports-tracker symbian nokia gps gpx
Platform: UNKNOWN
Classifier: Programming Language :: Python
Classifier: Programming Language :: Python :: 3
Classifier: License :: OSI Approved :: GNU Library or Lesser General Public License (LGPL)
Classifier: Operating System :: OS Independent
Classifier: Development Status :: 5 - Production/Stable
Requires-Python: >=3.6
License-File: LICENSE
